production_ready/__init__.py
production_ready/cli.py
production_ready/production_ready.py
production_ready-0.0.2.dist-info/LICENSE.txt
production_ready-0.0.2.dist-info/METADATA
production_ready-0.0.2.dist-info/WHEEL
production_ready-0.0.2.dist-info/entry_points.txt
production_ready-0.0.2.dist-info/top_level.txt
production_ready-0.0.2.dist-info/RECORD
