Metadata-Version: 2.1
Name: production_ready
Version: 0.0.2
Summary: ...
Author: Daniel Pepper
License: The MIT License (MIT)
Project-URL: Homepage, https://github.com/dpep/production_ready_py
Keywords: education
Classifier: License :: OSI Approved :: MIT License
Classifier: Topic :: Education
Classifier: Topic :: Internet :: WWW/HTTP
Requires-Python: >=3
License-File: LICENSE.txt
Requires-Dist: flask
